base64url.py
base64url-1.0.0.dist-info/METADATA
base64url-1.0.0.dist-info/WHEEL
base64url-1.0.0.dist-info/RECORD
