Metadata-Version: 2.4
Name: base64url
Version: 1.0.0
Summary: Base64 encoding without Python's base64 flaws. No padding, str types.
Project-URL: Homepage, https://git.zi.fi/leo/base64url-python
Project-URL: Repository, https://github.com/LeoVasanko/base64url-python
Author: Leo Vasanko
Keywords: b64url,base64,urlsafe_b64decode,urlsafe_b64encode
Classifier: Development Status :: 5 - Production/Stable
Classifier: Intended Audience :: Developers
Classifier: License :: OSI Approved :: MIT License
Classifier: License :: Public Domain
Classifier: Programming Language :: Python :: 3
Classifier: Topic :: Software Development :: Libraries :: Python Modules
Classifier: Topic :: Utilities
Requires-Python: >=3.8
